pyiwe/__init__.py
pyiwe/config.py
pyiwe/iwe.py
pyiwe/tests/testdata/bryocorini/SI_4_Bryocorinae_matrix.tnt
pyiwe/tests/testdata/bryocorini/bryocorini_fin.tre
pyiwe/tests/testscripts/hello_world.tnt
pyiwe/tnt_install/__init__.py
pyiwe/tnt_install/install_tnt_nix.sh
pyiwe/tnt_install/install_tnt_win.ps1
pyiwe/tnt_scripts/iwe_template.tnt
pyiwe/utils/__init__.py
pyiwe/utils/common.py
pyiwe/utils/processing.py
pyiwe/utils/visualize.py
pyiwe-0.0.8.post3.dist-info/LICENSE
pyiwe-0.0.8.post3.dist-info/METADATA
pyiwe-0.0.8.post3.dist-info/WHEEL
pyiwe-0.0.8.post3.dist-info/top_level.txt
pyiwe-0.0.8.post3.dist-info/RECORD
