Metadata-Version: 2.1
Name: pyiwe
Version: 0.0.8.post3
Summary: Python wrapper for TNT (Tree analysis using New Technology) implied weighting with clades support
Home-page: https://github.com/alexander-pv/pyiwe
Author: Alexander Popkov
Author-email: alr.popkov@gmail.com
License: MIT
Download-URL: https://pypi.org/project/pyiwe/#files
Platform: UNKNOWN
Classifier: Intended Audience :: Science/Research
Classifier: Intended Audience :: Developers
Classifier: License :: OSI Approved
Classifier: Operating System :: Unix
Classifier: Operating System :: Microsoft :: Windows
Classifier: Programming Language :: Python
Classifier: Programming Language :: Python :: 3.7
Classifier: Programming Language :: Python :: 3.8
Classifier: Programming Language :: Python :: 3.9
Requires-Python: <=3.9.19
License-File: LICENSE
Requires-Dist: ete3 >=3.1.2
Requires-Dist: biopython >=1.79
Requires-Dist: tqdm >=4.62.3
Requires-Dist: numpy >=1.19
Requires-Dist: pandas >=1.1.0
Requires-Dist: pillow >=8.4.0
Requires-Dist: seaborn >=0.11.2
Requires-Dist: matplotlib >=3.5.0
Requires-Dist: PyQt5 >=5.15.6
Requires-Dist: jupyter >=1.0.0
